odoo/addons/ddmrp_history/README.rst
odoo/addons/ddmrp_history/__init__.py
odoo/addons/ddmrp_history/__manifest__.py
odoo/addons/ddmrp_history/demo/ddmrp.history.csv
odoo/addons/ddmrp_history/i18n/ddmrp_history.pot
odoo/addons/ddmrp_history/i18n/es.po
odoo/addons/ddmrp_history/i18n/fr.po
odoo/addons/ddmrp_history/i18n/it.po
odoo/addons/ddmrp_history/models/__init__.py
odoo/addons/ddmrp_history/models/ddmrp_history.py
odoo/addons/ddmrp_history/models/stock_buffer.py
odoo/addons/ddmrp_history/readme/CONTRIBUTORS.md
odoo/addons/ddmrp_history/readme/CREDITS.md
odoo/addons/ddmrp_history/readme/DESCRIPTION.md
odoo/addons/ddmrp_history/readme/HISTORY.md
odoo/addons/ddmrp_history/readme/INSTALL.md
odoo/addons/ddmrp_history/readme/USAGE.md
odoo/addons/ddmrp_history/security/ir.model.access.csv
odoo/addons/ddmrp_history/security/security.xml
odoo/addons/ddmrp_history/static/description/icon.png
odoo/addons/ddmrp_history/static/description/index.html
odoo/addons/ddmrp_history/tests/__init__.py
odoo/addons/ddmrp_history/tests/test_ddmrp_history.py
odoo/addons/ddmrp_history/views/ddmrp_history_view.xml
odoo/addons/ddmrp_history/views/stock_buffer_view.xml
odoo_addon_ddmrp_history-18.0.1.2.0.dist-info/METADATA
odoo_addon_ddmrp_history-18.0.1.2.0.dist-info/WHEEL
odoo_addon_ddmrp_history-18.0.1.2.0.dist-info/top_level.txt
odoo_addon_ddmrp_history-18.0.1.2.0.dist-info/RECORD
